rainmaker_http/__init__.py
rainmaker_http/client.py
rainmaker_http/exceptions.py
rainmaker_http-0.0.3.dist-info/licenses/LICENSE
rainmaker_http-0.0.3.dist-info/METADATA
rainmaker_http-0.0.3.dist-info/WHEEL
rainmaker_http-0.0.3.dist-info/top_level.txt
rainmaker_http-0.0.3.dist-info/RECORD
