Metadata-Version: 2.4
Name: rainmaker-http
Version: 0.0.3
Summary: Minimal async HTTP client for ESP RainMaker (Zehnder Multi Controller)
Author-email: morphiumdeus <morphiumdeus@user.github.com>
Project-URL: Homepage, https://github.com/morphiumdeus/rainmaker-http
Project-URL: Repository, https://github.com/morphiumdeus/rainmaker-http
Requires-Python: >=3.11
License-File: LICENSE
Requires-Dist: aiohttp<4,>=3.8.1
Provides-Extra: dev
Requires-Dist: pytest>=7.0; extra == "dev"
Requires-Dist: pytest-asyncio>=0.20; extra == "dev"
Requires-Dist: ruff>=0.0.241; extra == "dev"
Requires-Dist: build; extra == "dev"
Requires-Dist: twine; extra == "dev"
Dynamic: license-file
